mseep_openfga_mcp-1.0.0.dist-info/licenses/LICENSE
tests/__init__.py
tests/integration/__init__.py
tests/integration/seed_fga.py
tests/integration/test_mcp_integration.py
tests/unit/__init__.py
tests/unit/test_openfga.py
tests/unit/test_server.py
mseep_openfga_mcp-1.0.0.dist-info/METADATA
mseep_openfga_mcp-1.0.0.dist-info/WHEEL
mseep_openfga_mcp-1.0.0.dist-info/top_level.txt
mseep_openfga_mcp-1.0.0.dist-info/RECORD
