Metadata-Version: 2.4
Name: mseep-openfga-mcp
Version: 1.0.0
Summary: Model Context Protocol (MCP) server for OpenFGA
Home-page: 
Author: mseep
Author-email: support@skydeck.ai
Maintainer: mseep
Maintainer-email: support@skydeck.ai
Keywords: mseep,git,mcp,llm,automation
Classifier: Programming Language :: Python :: 3
Classifier: License :: OSI Approved :: MIT License
Classifier: Operating System :: OS Independent
Requires-Python: >=3.6
License-File: LICENSE
Requires-Dist: httpx<0.29,>=0.28
Requires-Dist: mcp<2,>=1.4
Requires-Dist: openfga-sdk<1,>=0.9
Requires-Dist: starlette<0.47,>=0.27
Requires-Dist: uvicorn<0.35,>=0.23
Dynamic: author
Dynamic: author-email
Dynamic: classifier
Dynamic: description
Dynamic: description-content-type
Dynamic: keywords
Dynamic: license-file
Dynamic: maintainer
Dynamic: maintainer-email
Dynamic: requires-dist
Dynamic: requires-python
Dynamic: summary
